segment_embryo/__init__.py
segment_embryo/_sample_data.py
segment_embryo/_version.py
segment_embryo/_widget.py
segment_embryo/napari.yaml
segment_embryo/napari_util.py
segment_embryo/qtutil.py
segment_embryo/segmentation.py
segment_embryo/_tests/__init__.py
segment_embryo/_tests/test_sample_data.py
segment_embryo/_tests/test_widget.py
segment_embryo-0.5.dist-info/LICENSE
segment_embryo-0.5.dist-info/METADATA
segment_embryo-0.5.dist-info/WHEEL
segment_embryo-0.5.dist-info/entry_points.txt
segment_embryo-0.5.dist-info/top_level.txt
segment_embryo-0.5.dist-info/RECORD
