Metadata-Version: 2.2
Name: segment-embryo
Version: 0.5
Summary: 3D Segment ascidian embryos using cellpose. The images are first rescaled to be isotropic and then downscaled, before cellpose is used. The resulting labels are upscaled to match the original data.
Author: Volker Baecker
Author-email: volker.baecker@mri.cnrs.fr
License: 
Project-URL: Homepage, https://github.com/MontpellierRessourcesImagerie/segment-embryo
Project-URL: Documentation, https://github.com/MontpellierRessourcesImagerie/segment-embryo#segment-embryo
Project-URL: Repository, https://github.com/MontpellierRessourcesImagerie/segment-embryo.git
Project-URL: Issues, https://github.com/MontpellierRessourcesImagerie/segment-embryo/issues
Project-URL: Changelog, https://github.com/MontpellierRessourcesImagerie/segment-embryo/releases
Classifier: Development Status :: 2 - Pre-Alpha
Classifier: Framework :: napari
Classifier: Intended Audience :: Developers
Classifier: License :: OSI Approved :: MIT License
Classifier: Operating System :: OS Independent
Classifier: Programming Language :: Python
Classifier: Programming Language :: Python :: 3
Classifier: Programming Language :: Python :: 3 :: Only
Classifier: Programming Language :: Python :: 3.9
Classifier: Programming Language :: Python :: 3.10
Classifier: Programming Language :: Python :: 3.11
Classifier: Programming Language :: Python :: 3.12
Classifier: Topic :: Scientific/Engineering :: Image Processing
Requires-Python: >=3.9
License-File: LICENSE
Requires-Dist: numpy
Requires-Dist: magicgui
Requires-Dist: qtpy
Requires-Dist: scikit-image
Requires-Dist: cellpose
Requires-Dist: czifile
Requires-Dist: napari-czifile2
Requires-Dist: set-calibration
Requires-Dist: big-fish
Requires-Dist: napari-bigfish
Requires-Dist: scikit-image
Provides-Extra: testing
Requires-Dist: tox; extra == "testing"
Requires-Dist: pytest; extra == "testing"
Requires-Dist: pytest-cov; extra == "testing"
Requires-Dist: pytest-qt; extra == "testing"
Requires-Dist: napari; extra == "testing"
Requires-Dist: pyqt5; extra == "testing"
Requires-Dist: numpy; extra == "testing"
